odoo/addons/stock_reserve_sale/README.rst
odoo/addons/stock_reserve_sale/__init__.py
odoo/addons/stock_reserve_sale/__manifest__.py
odoo/addons/stock_reserve_sale/i18n/es.po
odoo/addons/stock_reserve_sale/i18n/fi.po
odoo/addons/stock_reserve_sale/i18n/fr.po
odoo/addons/stock_reserve_sale/i18n/stock_reserve_sale.pot
odoo/addons/stock_reserve_sale/migrations/13.0.1.1.0/post-migration.py
odoo/addons/stock_reserve_sale/model/__init__.py
odoo/addons/stock_reserve_sale/model/sale.py
odoo/addons/stock_reserve_sale/model/stock_reserve.py
odoo/addons/stock_reserve_sale/readme/CONTRIBUTORS.rst
odoo/addons/stock_reserve_sale/readme/DESCRIPTION.rst
odoo/addons/stock_reserve_sale/readme/USAGE.rst
odoo/addons/stock_reserve_sale/static/description/icon.png
odoo/addons/stock_reserve_sale/static/description/index.html
odoo/addons/stock_reserve_sale/tests/__init__.py
odoo/addons/stock_reserve_sale/tests/test_stock_reserve_sale.py
odoo/addons/stock_reserve_sale/view/sale.xml
odoo/addons/stock_reserve_sale/view/stock_reserve.xml
odoo/addons/stock_reserve_sale/wizard/__init__.py
odoo/addons/stock_reserve_sale/wizard/sale_stock_reserve.py
odoo/addons/stock_reserve_sale/wizard/sale_stock_reserve_view.xml
odoo13_addon_stock_reserve_sale-13.0.1.1.0.dist-info/METADATA
odoo13_addon_stock_reserve_sale-13.0.1.1.0.dist-info/WHEEL
odoo13_addon_stock_reserve_sale-13.0.1.1.0.dist-info/top_level.txt
odoo13_addon_stock_reserve_sale-13.0.1.1.0.dist-info/RECORD
